{
  "name": "Biblia",
  "books": {
    "Genesis": "Rodzaju",
    "Exodus": "Wyjścia",
    "Leviticus": "Kapłańska",
    "Numbers": "Liczb",
    "Deuteronomy": "Powtórzonego",
    "Joshua": "Jozuego",
    "Judges": "Sędziów",
    "Ruth": "Rut",
    "I Samuel": "1 Samuela",
    "II Samuel": "2 Samuela",
    "I Kings": "1 Królewska",
    "II Kings": "2 Królewska",
    "I Chronicles": "1 Kronik",
    "II Chronicles": "2 Kronik",
    "Ezra": "Ezdrasza",
    "Nehemiah": "Nehemiasza",
    "Esther": "Estery",
    "Job": "Joba",
    "Psalms": "Psalmy",
    "Proverbs": "Przypowieści",
    "Ecclesiastes": "Kaznodziei",
    "Song of Solomon": "Pieśni",
    "Isaiah": "Izajasza",
    "Jeremiah": "Jeremiasza",
    "Lamentations": "Treny",
    "Ezekiel": "Ezechiela",
    "Daniel": "Daniela",
    "Hosea": "Ozeasza",
    "Joel": "Joela",
    "Amos": "Amosa",
    "Obadiah": "Abdiasza",
    "Jonah": "Jonasza",
    "Micah": "Micheasza",
    "Nahum": "Nahuma",
    "Habakkuk": "Habakuka",
    "Zephaniah": "Sofoniasza",
    "Haggai": "Aggeusza",
    "Zechariah": "Zachariasza",
    "Malachi": "Malachiasza",
    "Matthew": "Mateusza",
    "Mark": "Marka",
    "Luke": "Łukasza",
    "John": "Jana",
    "Acts": "Dzieje",
    "Romans": "Rzymian",
    "I Corinthians": "1 Koryntian",
    "II Corinthians": "2 Koryntian",
    "Galatians": "Galacjan",
    "Ephesians": "Efezjan",
    "Philippians": "Filipian",
    "Colossians": "Kolosan",
    "I Thessalonians": "1 Tesaloniczan",
    "II Thessalonians": "2 Tesaloniczan",
    "I Timothy": "1 Tymoteusza",
    "II Timothy": "2 Tymoteusza",
    "Titus": "Tytusa",
    "Philemon": "Filemona",
    "Hebrews": "Hebrajczyków",
    "James": "Jakuba",
    "I Peter": "1 Piotra",
    "II Peter": "2 Piotra",
    "I John": "1 Jana",
    "II John": "2 Jana",
    "III John": "3 Jana",
    "Jude": "Judy",
    "Revelation of John": "Objawienie"
  }
}
